{
  "dataset": "coerde-events",
  "description": "Öffentliche Veranstaltungen in Münster-Coerde",
  "license": "CC-BY-4.0",
  "generated_at": "2026-06-19T07:47:18.542Z",
  "event_count": 70,
  "events": [
    {
      "event_id": "2026-06-19_0415_lesen_mit_kleinen_wesen_stadtbuecherei_coerde",
      "title": "Lesen mit kleinen Wesen",
      "start_date": "2026-06-19",
      "start_time": "04:15",
      "end_date": "2026-06-19",
      "end_time": null,
      "location_name": "Stadtbücherei Coerde",
      "address": "Hamannplatz, 48157 Münster",
      "city": "Münster-Coerde",
      "organizer": "Stadtbücherei Münster",
      "category": "Lesung / Bildung / Stadtteil",
      "short_description": "Vorlesestunde für Kleinkinder mit Eltern oder Tageseltern, altersgerechte Geschichten gemütlich vorgelesen.",
      "status": "scheduled",
      "source_name": "Stadtbücherei Coerde – Veranstaltungen",
      "source_url": "https://www.stadt-muenster.de/buecherei/orte-und-oeffnungszeiten/coerde/veranstaltungen",
      "source_id": "stadtbuecherei_coerde",
      "confidence": "0,9",
      "last_updated": "2026-06-19T07:47:18.542Z"
    },
    {
      "event_id": "2026-06-19_1530_projekt_madchen_starken_awo_coerde_mittendrin",
      "title": "Projekt „Mädchen stärken“",
      "start_date": "2026-06-19",
      "start_time": "15:30",
      "end_date": "2026-06-19",
      "end_time": "17:00",
      "location_name": "AWO Coerde mittendrin",
      "address": "Königsberger Straße 8, 48157 Münster-Coerde",
      "city": "Münster-Coerde",
      "organizer": "AWO Coerde mittendrin",
      "category": "Stadtteil / Begegnung / Beratung",
      "short_description": "Projekt „Mädchen stärken“: wöchentliches Angebot jeden Freitag im AWO Coerde mittendrin der AWO in Münster-Coerde.",
      "status": "scheduled",
      "source_name": "AWO Coerde mittendrin",
      "source_url": "https://www.awo-msl-re.de/einrichtung/coerde-mittendrin",
      "source_id": "awo_coerde_mittendrin",
      "confidence": "0,9",
      "last_updated": "2026-06-19T07:47:18.542Z"
    },
    {
      "event_id": "2026-06-19_1630_madchenprojekt_gemeinsam_sichtbar_stark_madchen_aus_coerde_gsmc_iriba_brunnen_termine",
      "title": "Mädchenprojekt: Gemeinsam sichtbar & stark – Mädchen aus Coerde (GSMC)",
      "start_date": "2026-06-19",
      "start_time": "16:30",
      "end_date": "2026-06-19",
      "end_time": "18:00",
      "location_name": "coerde mittendrin",
      "address": "Königsberger Straße 8, 48157 Münster",
      "city": "Münster-Coerde",
      "organizer": "Iriba-Brunnen e.V.",
      "category": "Stadtteil / Begegnung / Engagement",
      "short_description": "Workshop für Mädchen aus Coerde zur Stärkung und Sichtbarkeit in der Gemeinschaft.",
      "status": "scheduled",
      "source_name": "Iriba-Brunnen – Termine",
      "source_url": "https://www.iriba-brunnen.de/termine/",
      "source_id": "iriba_brunnen_termine",
      "confidence": "0,9",
      "last_updated": "2026-06-19T07:47:18.542Z"
    },
    {
      "event_id": "2026-06-20_1500_nachhilfeangebot_awo_coerde_mittendrin",
      "title": "Nachhilfeangebot",
      "start_date": "2026-06-20",
      "start_time": "15:00",
      "end_date": "2026-06-20",
      "end_time": "17:00",
      "location_name": "AWO Coerde mittendrin",
      "address": "Königsberger Straße 8, 48157 Münster-Coerde",
      "city": "Münster-Coerde",
      "organizer": "AWO Coerde mittendrin",
      "category": "Stadtteil / Begegnung / Beratung",
      "short_description": "Nachhilfeangebot: wöchentliches Angebot jeden Samstag im AWO Coerde mittendrin der AWO in Münster-Coerde.",
      "status": "scheduled",
      "source_name": "AWO Coerde mittendrin",
      "source_url": "https://www.awo-msl-re.de/einrichtung/coerde-mittendrin",
      "source_id": "awo_coerde_mittendrin",
      "confidence": "0,9",
      "last_updated": "2026-06-19T07:47:18.542Z"
    },
    {
      "event_id": "2026-06-21_0930_gottesdienst_andreas_kirchengemeinde_startseite",
      "title": "Gottesdienst",
      "start_date": "2026-06-21",
      "start_time": "09:30",
      "end_date": "2026-06-21",
      "end_time": null,
      "location_name": "Andreas-Kirchengemeinde Münster-Coerde",
      "address": "Münster-Coerde",
      "city": "Münster-Coerde",
      "organizer": "Ev. Andreas-Kirchengemeinde Münster-Coerde",
      "category": "Kirche / Stadtteil / Begegnung",
      "short_description": "Gottesdienst am 21. Juni 2026 um 09:30 Uhr in der Andreas-Kirchengemeinde Münster-Coerde.",
      "status": "scheduled",
      "source_name": "Ev. Andreas-Kirchengemeinde Münster-Coerde – Startseite",
      "source_url": "https://www.andreas-kirchengemeinde-muenster.de/",
      "source_id": "andreas_kirchengemeinde_startseite",
      "confidence": "0,9",
      "last_updated": "2026-06-19T07:47:18.542Z"
    },
    {
      "event_id": "2026-06-21_1200_qi_gong_seminar_die_wandlungsphase_feuer_meerwiese_begegnungszentrum",
      "title": "Qi Gong – Seminar Die Wandlungsphase Feuer",
      "start_date": "2026-06-21",
      "start_time": "12:00",
      "end_date": "2026-06-21",
      "end_time": "19:00",
      "location_name": "Begegnungszentrum Meerwiese",
      "address": "An der Meerwiese 25, 48157 Münster-Coerde",
      "city": "Münster-Coerde",
      "organizer": "Volker Nowak-von der Way, Qi-Gong-Lehrer",
      "category": "Stadtteil / Begegnung / Kultur",
      "short_description": "Seminar mit Übungen zur Harmonisierung des Herzens nach Traditioneller Chinesischer Medizin. Bewegungs- und meditative Übungen zur Förderung von Leichtigkeit und freiem Qi-Fluss. Vorkenntnisse nicht erforderlich.",
      "status": "scheduled",
      "source_name": "Meerwiese – Begegnungszentrum Veranstaltungen",
      "source_url": "https://www.stadt-muenster.de/meerwiese/begegnungszentrum/veranstaltungen",
      "source_id": "meerwiese_begegnungszentrum",
      "confidence": "0,9",
      "last_updated": "2026-06-19T07:47:18.542Z"
    },
    {
      "event_id": "2026-06-22_1430_offener_spieletreff_fur_senior_innen_doppelkopfrunde_alter_werden_in_coerde_awo_coerde_mittendrin",
      "title": "Offener Spieletreff für Senior*innen / Doppelkopfrunde \"Älter werden in Coerde\"",
      "start_date": "2026-06-22",
      "start_time": "14:30",
      "end_date": "2026-06-22",
      "end_time": "17:00",
      "location_name": "AWO Coerde mittendrin",
      "address": "Königsberger Straße 8, 48157 Münster-Coerde",
      "city": "Münster-Coerde",
      "organizer": "AWO Coerde mittendrin",
      "category": "Stadtteil / Begegnung / Beratung",
      "short_description": "Offener Spieletreff für Senior*innen / Doppelkopfrunde \"Älter werden in Coerde\": wöchentliches Angebot jeden Montag im AWO Coerde mittendrin der AWO in Münster-Coerde.",
      "status": "scheduled",
      "source_name": "AWO Coerde mittendrin",
      "source_url": "https://www.awo-msl-re.de/einrichtung/coerde-mittendrin",
      "source_id": "awo_coerde_mittendrin",
      "confidence": "0,9",
      "last_updated": "2026-06-19T07:47:18.542Z"
    },
    {
      "event_id": "2026-06-23_1100_kochprojekt_gemeinsam_am_herd_rezepte_ohne_grenzen_awo_coerde_mittendrin",
      "title": "Kochprojekt „Gemeinsam am Herd – Rezepte ohne Grenzen“",
      "start_date": "2026-06-23",
      "start_time": "11:00",
      "end_date": "2026-06-23",
      "end_time": "14:00",
      "location_name": "AWO Coerde mittendrin",
      "address": "Königsberger Straße 8, 48157 Münster-Coerde",
      "city": "Münster-Coerde",
      "organizer": "AWO Coerde mittendrin",
      "category": "Stadtteil / Begegnung / Beratung",
      "short_description": "Kochprojekt „Gemeinsam am Herd – Rezepte ohne Grenzen“: wöchentliches Angebot jeden Dienstag im AWO Coerde mittendrin der AWO in Münster-Coerde.",
      "status": "scheduled",
      "source_name": "AWO Coerde mittendrin",
      "source_url": "https://www.awo-msl-re.de/einrichtung/coerde-mittendrin",
      "source_id": "awo_coerde_mittendrin",
      "confidence": "0,9",
      "last_updated": "2026-06-19T07:47:18.542Z"
    },
    {
      "event_id": "2026-06-24_0900_migrationsberatung_mbe_in_munster_coerde_drk_munster_migrationsberatung_mbe",
      "title": "Migrationsberatung (MBE) in Münster-Coerde",
      "start_date": "2026-06-24",
      "start_time": "09:00",
      "end_date": "2026-06-24",
      "end_time": "15:00",
      "location_name": "DRK Münster – Migrationsberatung",
      "address": "Hamannplatz 26/28, 48157 Münster-Coerde",
      "city": "Münster-Coerde",
      "organizer": "Deutsches Rotes Kreuz Münster",
      "category": "",
      "short_description": "Wöchentliche Migrationsberatung für erwachsene Neuzugewanderte ab 28 Jahren mit Unterstützung in Integrationsfragen, Behördenangelegenheiten und sozialer Teilhabe, mittwochs von 9 bis 15 Uhr in Coerde.",
      "status": "scheduled",
      "source_name": "DRK Münster – Migrationsberatung (MBE)",
      "source_url": "https://www.drk-muenster.de/angebot/migrationsberatung.html",
      "source_id": "drk_munster_migrationsberatung_mbe",
      "confidence": "0,9",
      "last_updated": "2026-06-19T07:47:18.542Z"
    },
    {
      "event_id": "2026-06-24_1000_fruhstuckstreff_mit_anmeldung_unter_tel_01520_9123615_awo_coerde_mittendrin",
      "title": "Frühstückstreff (mit Anmeldung unter Tel.: 01520 9123615)",
      "start_date": "2026-06-24",
      "start_time": "10:00",
      "end_date": "2026-06-24",
      "end_time": "12:00",
      "location_name": "AWO Coerde mittendrin",
      "address": "Königsberger Straße 8, 48157 Münster-Coerde",
      "city": "Münster-Coerde",
      "organizer": "AWO Coerde mittendrin",
      "category": "Stadtteil / Begegnung / Beratung",
      "short_description": "Frühstückstreff (mit Anmeldung unter Tel.: 01520 9123615): wöchentliches Angebot jeden Mittwoch im AWO Coerde mittendrin der AWO in Münster-Coerde.",
      "status": "scheduled",
      "source_name": "AWO Coerde mittendrin",
      "source_url": "https://www.awo-msl-re.de/einrichtung/coerde-mittendrin",
      "source_id": "awo_coerde_mittendrin",
      "confidence": "0,9",
      "last_updated": "2026-06-19T07:47:18.542Z"
    },
    {
      "event_id": "2026-06-24_1300_wochentliche_offene_beratungszeit_empowerment_rassismuskritik_nachhaltigkeit_koo_iriba_brunnen_termine",
      "title": "Wöchentliche offene Beratungszeit – Empowerment / Rassismuskritik / Nachhaltigkeit & Kooperationen",
      "start_date": "2026-06-24",
      "start_time": "13:00",
      "end_date": "2026-06-24",
      "end_time": "15:00",
      "location_name": "coerde mittendrin",
      "address": "Königsberger Straße 8, 48157 Münster",
      "city": "Münster-Coerde",
      "organizer": "Iriba-Brunnen e.V.",
      "category": "Stadtteil / Begegnung / Engagement",
      "short_description": "Wöchentliche offene Beratungszeit zu Empowerment, Rassismuskritik, Nachhaltigkeit und Kooperationen.",
      "status": "scheduled",
      "source_name": "Iriba-Brunnen – Termine",
      "source_url": "https://www.iriba-brunnen.de/termine/",
      "source_id": "iriba_brunnen_termine",
      "confidence": "0,9",
      "last_updated": "2026-06-19T07:47:18.542Z"
    },
    {
      "event_id": "2026-06-24_1800_heimat_remixed_musik_der_kulturen_iriba_brunnen_termine",
      "title": "Heimat remixed – Musik der Kulturen",
      "start_date": "2026-06-24",
      "start_time": "18:00",
      "end_date": "2026-06-24",
      "end_time": "20:30",
      "location_name": "Franziskushaus in Coerde",
      "address": "Schneidemühlerstr. 23, 48157 Münster",
      "city": "Münster-Coerde",
      "organizer": "Iriba-Brunnen e.V.",
      "category": "Stadtteil / Begegnung / Engagement",
      "short_description": "Musikalische Veranstaltung mit vielfältigen kulturellen Einflüssen im Franziskushaus Coerde.",
      "status": "scheduled",
      "source_name": "Iriba-Brunnen – Termine",
      "source_url": "https://www.iriba-brunnen.de/termine/",
      "source_id": "iriba_brunnen_termine",
      "confidence": "0,9",
      "last_updated": "2026-06-19T07:47:18.542Z"
    },
    {
      "event_id": "2026-06-25_1100_offene_sprechstunde_coerde_mittendrin_awo_coerde_mittendrin",
      "title": "Offene Sprechstunde „coerde mittendrin“",
      "start_date": "2026-06-25",
      "start_time": "11:00",
      "end_date": "2026-06-25",
      "end_time": "13:00",
      "location_name": "AWO Coerde mittendrin",
      "address": "Königsberger Straße 8, 48157 Münster-Coerde",
      "city": "Münster-Coerde",
      "organizer": "AWO Coerde mittendrin",
      "category": "Stadtteil / Begegnung / Beratung",
      "short_description": "Offene Sprechstunde „coerde mittendrin“: wöchentliches Angebot jeden Donnerstag im AWO Coerde mittendrin der AWO in Münster-Coerde.",
      "status": "scheduled",
      "source_name": "AWO Coerde mittendrin",
      "source_url": "https://www.awo-msl-re.de/einrichtung/coerde-mittendrin",
      "source_id": "awo_coerde_mittendrin",
      "confidence": "0,9",
      "last_updated": "2026-06-19T07:47:18.542Z"
    },
    {
      "event_id": "2026-06-25_1900_zumba_in_coerde_ev_fabi_coerde",
      "title": "Zumba in Coerde",
      "start_date": "2026-06-25",
      "start_time": "19:00",
      "end_date": "2026-06-25",
      "end_time": null,
      "location_name": "Hauptschule Coerde - Musikraum",
      "address": "Münster-Coerde",
      "city": "Münster-Coerde",
      "organizer": "Ev. Familienbildungsstätte Münster",
      "category": "Bildung / Familie / Stadtteil",
      "short_description": "Wöchentlicher Zumba-Kurs in Coerde, beginnend ab dem 16. April 2026, jeweils donnerstags um 19:00 Uhr im Musikraum der Hauptschule Coerde.",
      "status": "scheduled",
      "source_name": "Ev. Familienbildungsstätte Münster – Coerde",
      "source_url": "https://www.ev-fabi-ms.de/programm/fabi-vor-ort/kategorie/Coerde/23",
      "source_id": "ev_fabi_coerde",
      "confidence": "0,9",
      "last_updated": "2026-06-19T07:47:18.542Z"
    },
    {
      "event_id": "2026-06-26_1400_improkids_improvisations_theater_workshop_kulturinitiative_coerde",
      "title": "IMPROkids – Improvisations-Theater-Workshop",
      "start_date": "2026-06-26",
      "start_time": "14:00",
      "end_date": "2026-06-27",
      "end_time": "16:00",
      "location_name": "",
      "address": "",
      "city": "Münster-Coerde",
      "organizer": "DRK Jugendtreff Münster-Coerde",
      "category": "Kultur / Stadtteil / Ehrenamt",
      "short_description": "| DRK Jugendtreff Münster-Coerde 01775250574 l a esner r - ter. Zum Kalender hinzufügen Google Kalender iCalendar Outlook 365 Outlook Live",
      "status": "scheduled",
      "source_name": "Kulturinitiative Coerde",
      "source_url": "https://kulturinitiative-coerde.de/",
      "source_id": "kulturinitiative_coerde",
      "confidence": "0,9",
      "last_updated": "2026-06-19T07:47:18.542Z"
    },
    {
      "event_id": "2026-06-26_1530_projekt_madchen_starken_awo_coerde_mittendrin",
      "title": "Projekt „Mädchen stärken“",
      "start_date": "2026-06-26",
      "start_time": "15:30",
      "end_date": "2026-06-26",
      "end_time": "17:00",
      "location_name": "AWO Coerde mittendrin",
      "address": "Königsberger Straße 8, 48157 Münster-Coerde",
      "city": "Münster-Coerde",
      "organizer": "AWO Coerde mittendrin",
      "category": "Stadtteil / Begegnung / Beratung",
      "short_description": "Projekt „Mädchen stärken“: wöchentliches Angebot jeden Freitag im AWO Coerde mittendrin der AWO in Münster-Coerde.",
      "status": "scheduled",
      "source_name": "AWO Coerde mittendrin",
      "source_url": "https://www.awo-msl-re.de/einrichtung/coerde-mittendrin",
      "source_id": "awo_coerde_mittendrin",
      "confidence": "0,9",
      "last_updated": "2026-06-19T07:47:18.542Z"
    },
    {
      "event_id": "2026-06-27_1500_nachhilfeangebot_awo_coerde_mittendrin",
      "title": "Nachhilfeangebot",
      "start_date": "2026-06-27",
      "start_time": "15:00",
      "end_date": "2026-06-27",
      "end_time": "17:00",
      "location_name": "AWO Coerde mittendrin",
      "address": "Königsberger Straße 8, 48157 Münster-Coerde",
      "city": "Münster-Coerde",
      "organizer": "AWO Coerde mittendrin",
      "category": "Stadtteil / Begegnung / Beratung",
      "short_description": "Nachhilfeangebot: wöchentliches Angebot jeden Samstag im AWO Coerde mittendrin der AWO in Münster-Coerde.",
      "status": "scheduled",
      "source_name": "AWO Coerde mittendrin",
      "source_url": "https://www.awo-msl-re.de/einrichtung/coerde-mittendrin",
      "source_id": "awo_coerde_mittendrin",
      "confidence": "0,9",
      "last_updated": "2026-06-19T07:47:18.542Z"
    },
    {
      "event_id": "2026-06-27_1800_stadtteilkonzert_meerwiese_theater",
      "title": "Stadtteilkonzert",
      "start_date": "2026-06-27",
      "start_time": "18:00",
      "end_date": "2026-06-27",
      "end_time": null,
      "location_name": "Begegnungszentrum Meerwiese",
      "address": "An der Meerwiese 25, 48157 Münster-Coerde",
      "city": "Münster-Coerde",
      "organizer": "Symphonieorchester Münster",
      "category": "Theater / Kultur / Tanz / Kinderkultur",
      "short_description": "Konzert des Symphonieorchesters Münster im Begegnungszentrum Meerwiese am 27. Juni 2026 um 18 Uhr.",
      "status": "scheduled",
      "source_name": "Meerwiese – Stücke und Termine",
      "source_url": "https://www.stadt-muenster.de/meerwiese/theater/stuecke-und-termine",
      "source_id": "meerwiese_theater",
      "confidence": "0,9",
      "last_updated": "2026-06-19T07:47:18.542Z"
    },
    {
      "event_id": "2026-06-28_1100_gottesdienst_mit_dem_andreas_singekreis_andreas_kirchengemeinde_startseite",
      "title": "Gottesdienst mit dem Andreas-Singekreis",
      "start_date": "2026-06-28",
      "start_time": "11:00",
      "end_date": "2026-06-28",
      "end_time": null,
      "location_name": "Andreas-Kirchengemeinde Münster-Coerde",
      "address": "Münster-Coerde",
      "city": "Münster-Coerde",
      "organizer": "Ev. Andreas-Kirchengemeinde Münster-Coerde",
      "category": "Kirche / Stadtteil / Begegnung",
      "short_description": "Gottesdienst mit dem Andreas-Singekreis am 28. Juni 2026 um 11:00 Uhr in der Andreas-Kirchengemeinde Münster-Coerde.",
      "status": "scheduled",
      "source_name": "Ev. Andreas-Kirchengemeinde Münster-Coerde – Startseite",
      "source_url": "https://www.andreas-kirchengemeinde-muenster.de/",
      "source_id": "andreas_kirchengemeinde_startseite",
      "confidence": "0,9",
      "last_updated": "2026-06-19T07:47:18.542Z"
    },
    {
      "event_id": "2026-06-28_1530_erwachsen_meerwiese_theater",
      "title": "Erwachsen?!",
      "start_date": "2026-06-28",
      "start_time": "15:30",
      "end_date": "2026-06-28",
      "end_time": null,
      "location_name": "Begegnungszentrum Meerwiese",
      "address": "An der Meerwiese 25, 48157 Münster-Coerde",
      "city": "Münster-Coerde",
      "organizer": "theater satt aus München",
      "category": "Theater / Kultur / Tanz / Kinderkultur",
      "short_description": "Theaterstück von Veronika Wolff und Dominik Burki für alle ab 6 Jahren am 28. Juni 2026 um 15:30 Uhr.",
      "status": "scheduled",
      "source_name": "Meerwiese – Stücke und Termine",
      "source_url": "https://www.stadt-muenster.de/meerwiese/theater/stuecke-und-termine",
      "source_id": "meerwiese_theater",
      "confidence": "0,9",
      "last_updated": "2026-06-19T07:47:18.542Z"
    },
    {
      "event_id": "2026-06-29_1430_offener_spieletreff_fur_senior_innen_doppelkopfrunde_alter_werden_in_coerde_awo_coerde_mittendrin",
      "title": "Offener Spieletreff für Senior*innen / Doppelkopfrunde \"Älter werden in Coerde\"",
      "start_date": "2026-06-29",
      "start_time": "14:30",
      "end_date": "2026-06-29",
      "end_time": "17:00",
      "location_name": "AWO Coerde mittendrin",
      "address": "Königsberger Straße 8, 48157 Münster-Coerde",
      "city": "Münster-Coerde",
      "organizer": "AWO Coerde mittendrin",
      "category": "Stadtteil / Begegnung / Beratung",
      "short_description": "Offener Spieletreff für Senior*innen / Doppelkopfrunde \"Älter werden in Coerde\": wöchentliches Angebot jeden Montag im AWO Coerde mittendrin der AWO in Münster-Coerde.",
      "status": "scheduled",
      "source_name": "AWO Coerde mittendrin",
      "source_url": "https://www.awo-msl-re.de/einrichtung/coerde-mittendrin",
      "source_id": "awo_coerde_mittendrin",
      "confidence": "0,9",
      "last_updated": "2026-06-19T07:47:18.542Z"
    },
    {
      "event_id": "2026-06-30_1100_kochprojekt_gemeinsam_am_herd_rezepte_ohne_grenzen_awo_coerde_mittendrin",
      "title": "Kochprojekt „Gemeinsam am Herd – Rezepte ohne Grenzen“",
      "start_date": "2026-06-30",
      "start_time": "11:00",
      "end_date": "2026-06-30",
      "end_time": "14:00",
      "location_name": "AWO Coerde mittendrin",
      "address": "Königsberger Straße 8, 48157 Münster-Coerde",
      "city": "Münster-Coerde",
      "organizer": "AWO Coerde mittendrin",
      "category": "Stadtteil / Begegnung / Beratung",
      "short_description": "Kochprojekt „Gemeinsam am Herd – Rezepte ohne Grenzen“: wöchentliches Angebot jeden Dienstag im AWO Coerde mittendrin der AWO in Münster-Coerde.",
      "status": "scheduled",
      "source_name": "AWO Coerde mittendrin",
      "source_url": "https://www.awo-msl-re.de/einrichtung/coerde-mittendrin",
      "source_id": "awo_coerde_mittendrin",
      "confidence": "0,9",
      "last_updated": "2026-06-19T07:47:18.542Z"
    },
    {
      "event_id": "2026-07-01_0900_migrationsberatung_mbe_in_munster_coerde_drk_munster_migrationsberatung_mbe",
      "title": "Migrationsberatung (MBE) in Münster-Coerde",
      "start_date": "2026-07-01",
      "start_time": "09:00",
      "end_date": "2026-07-01",
      "end_time": "15:00",
      "location_name": "DRK Münster – Migrationsberatung",
      "address": "Hamannplatz 26/28, 48157 Münster-Coerde",
      "city": "Münster-Coerde",
      "organizer": "Deutsches Rotes Kreuz Münster",
      "category": "",
      "short_description": "Wöchentliche Migrationsberatung für erwachsene Neuzugewanderte ab 28 Jahren mit Unterstützung in Integrationsfragen, Behördenangelegenheiten und sozialer Teilhabe, mittwochs von 9 bis 15 Uhr in Coerde.",
      "status": "scheduled",
      "source_name": "DRK Münster – Migrationsberatung (MBE)",
      "source_url": "https://www.drk-muenster.de/angebot/migrationsberatung.html",
      "source_id": "drk_munster_migrationsberatung_mbe",
      "confidence": "0,9",
      "last_updated": "2026-06-19T07:47:18.542Z"
    },
    {
      "event_id": "2026-07-01_1000_fruhstuckstreff_mit_anmeldung_unter_tel_01520_9123615_awo_coerde_mittendrin",
      "title": "Frühstückstreff (mit Anmeldung unter Tel.: 01520 9123615)",
      "start_date": "2026-07-01",
      "start_time": "10:00",
      "end_date": "2026-07-01",
      "end_time": "12:00",
      "location_name": "AWO Coerde mittendrin",
      "address": "Königsberger Straße 8, 48157 Münster-Coerde",
      "city": "Münster-Coerde",
      "organizer": "AWO Coerde mittendrin",
      "category": "Stadtteil / Begegnung / Beratung",
      "short_description": "Frühstückstreff (mit Anmeldung unter Tel.: 01520 9123615): wöchentliches Angebot jeden Mittwoch im AWO Coerde mittendrin der AWO in Münster-Coerde.",
      "status": "scheduled",
      "source_name": "AWO Coerde mittendrin",
      "source_url": "https://www.awo-msl-re.de/einrichtung/coerde-mittendrin",
      "source_id": "awo_coerde_mittendrin",
      "confidence": "0,9",
      "last_updated": "2026-06-19T07:47:18.542Z"
    },
    {
      "event_id": "2026-07-01_1300_wochentliche_offene_beratungszeit_empowerment_rassismuskritik_nachhaltigkeit_koo_iriba_brunnen_termine",
      "title": "Wöchentliche offene Beratungszeit – Empowerment / Rassismuskritik / Nachhaltigkeit & Kooperationen",
      "start_date": "2026-07-01",
      "start_time": "13:00",
      "end_date": "2026-07-01",
      "end_time": "15:00",
      "location_name": "coerde mittendrin",
      "address": "Königsberger Straße 8, 48157 Münster",
      "city": "Münster-Coerde",
      "organizer": "Iriba-Brunnen e.V.",
      "category": "Stadtteil / Begegnung / Engagement",
      "short_description": "Wöchentliche offene Beratungszeit zu Empowerment, Rassismuskritik, Nachhaltigkeit und Kooperationen.",
      "status": "scheduled",
      "source_name": "Iriba-Brunnen – Termine",
      "source_url": "https://www.iriba-brunnen.de/termine/",
      "source_id": "iriba_brunnen_termine",
      "confidence": "0,9",
      "last_updated": "2026-06-19T07:47:18.542Z"
    },
    {
      "event_id": "2026-07-02_1200_polizeisprechstunde_coerde_mittendrin_awo_coerde_mittendrin",
      "title": "Polizeisprechstunde „coerde-mittendrin“",
      "start_date": "2026-07-02",
      "start_time": "12:00",
      "end_date": "2026-07-02",
      "end_time": "13:00",
      "location_name": "AWO Coerde mittendrin",
      "address": "Königsberger Straße 8, 48157 Münster-Coerde",
      "city": "Münster-Coerde",
      "organizer": "AWO Coerde mittendrin",
      "category": "Stadtteil / Begegnung / Beratung",
      "short_description": "Polizeisprechstunde „coerde-mittendrin“: monatliches Angebot am ersten Donnerstag im Monat im AWO Coerde mittendrin der AWO in Münster-Coerde.",
      "status": "scheduled",
      "source_name": "AWO Coerde mittendrin",
      "source_url": "https://www.awo-msl-re.de/einrichtung/coerde-mittendrin",
      "source_id": "awo_coerde_mittendrin",
      "confidence": "0,9",
      "last_updated": "2026-06-19T07:47:18.542Z"
    },
    {
      "event_id": "2026-07-02_1900_zumba_in_coerde_ev_fabi_coerde",
      "title": "Zumba in Coerde",
      "start_date": "2026-07-02",
      "start_time": "19:00",
      "end_date": "2026-07-02",
      "end_time": null,
      "location_name": "Hauptschule Coerde - Musikraum",
      "address": "Münster-Coerde",
      "city": "Münster-Coerde",
      "organizer": "Ev. Familienbildungsstätte Münster",
      "category": "Bildung / Familie / Stadtteil",
      "short_description": "Wöchentlicher Zumba-Kurs in Coerde, beginnend ab dem 16. April 2026, jeweils donnerstags um 19:00 Uhr im Musikraum der Hauptschule Coerde.",
      "status": "scheduled",
      "source_name": "Ev. Familienbildungsstätte Münster – Coerde",
      "source_url": "https://www.ev-fabi-ms.de/programm/fabi-vor-ort/kategorie/Coerde/23",
      "source_id": "ev_fabi_coerde",
      "confidence": "0,9",
      "last_updated": "2026-06-19T07:47:18.542Z"
    },
    {
      "event_id": "2026-07-03_1030_tanzxchange_freie_tanzszene_munster_open_class_improvisation_leila_bakthali_meerwiese_begegnungszentrum",
      "title": "TanzXchange – Freie Tanzszene Münster: OPEN CLASS Improvisation - Leila Bakthali",
      "start_date": "2026-07-03",
      "start_time": "10:30",
      "end_date": "2026-07-03",
      "end_time": "12:00",
      "location_name": "Begegnungszentrum Meerwiese",
      "address": "An der Meerwiese 25, 48157 Münster-Coerde",
      "city": "Münster-Coerde",
      "organizer": "Melanie López López, Tänzerin und Mitbegründerin des Kollektivergissmeinnicht",
      "category": "Stadtteil / Begegnung / Kultur",
      "short_description": "Offene Tanzklasse mit Fokus auf Improvisation unter Leitung von Leila Bakthali. Teil der Initiative zur Förderung der Tanzszene in Münster.",
      "status": "scheduled",
      "source_name": "Meerwiese – Begegnungszentrum Veranstaltungen",
      "source_url": "https://www.stadt-muenster.de/meerwiese/begegnungszentrum/veranstaltungen",
      "source_id": "meerwiese_begegnungszentrum",
      "confidence": "0,9",
      "last_updated": "2026-06-19T07:47:18.542Z"
    },
    {
      "event_id": "2026-07-03_1530_projekt_madchen_starken_awo_coerde_mittendrin",
      "title": "Projekt „Mädchen stärken“",
      "start_date": "2026-07-03",
      "start_time": "15:30",
      "end_date": "2026-07-03",
      "end_time": "17:00",
      "location_name": "AWO Coerde mittendrin",
      "address": "Königsberger Straße 8, 48157 Münster-Coerde",
      "city": "Münster-Coerde",
      "organizer": "AWO Coerde mittendrin",
      "category": "Stadtteil / Begegnung / Beratung",
      "short_description": "Projekt „Mädchen stärken“: wöchentliches Angebot jeden Freitag im AWO Coerde mittendrin der AWO in Münster-Coerde.",
      "status": "scheduled",
      "source_name": "AWO Coerde mittendrin",
      "source_url": "https://www.awo-msl-re.de/einrichtung/coerde-mittendrin",
      "source_id": "awo_coerde_mittendrin",
      "confidence": "0,9",
      "last_updated": "2026-06-19T07:47:18.542Z"
    },
    {
      "event_id": "2026-07-04_0930_gemeinsames_fruhstuck_awo_coerde_mittendrin",
      "title": "Gemeinsames Frühstück",
      "start_date": "2026-07-04",
      "start_time": "09:30",
      "end_date": "2026-07-04",
      "end_time": "11:30",
      "location_name": "AWO Coerde mittendrin",
      "address": "Königsberger Straße 8, 48157 Münster-Coerde",
      "city": "Münster-Coerde",
      "organizer": "AWO Coerde mittendrin",
      "category": "Stadtteil / Begegnung / Beratung",
      "short_description": "Gemeinsames Frühstück: monatliches Angebot am ersten Samstag im Monat im AWO Coerde mittendrin der AWO in Münster-Coerde.",
      "status": "scheduled",
      "source_name": "AWO Coerde mittendrin",
      "source_url": "https://www.awo-msl-re.de/einrichtung/coerde-mittendrin",
      "source_id": "awo_coerde_mittendrin",
      "confidence": "0,9",
      "last_updated": "2026-06-19T07:47:18.542Z"
    },
    {
      "event_id": "2026-07-05_1330_a_taste_of_nature_workshop_wilde_fermente_eckels_kladde_events",
      "title": "A taste of:NATURE - Workshop - Wilde Fermente",
      "start_date": "2026-07-05",
      "start_time": "13:30",
      "end_date": "2026-07-05",
      "end_time": "15:30",
      "location_name": "Eckels Kladde",
      "address": "Coermühle 50f",
      "city": "Münster-Coerde",
      "organizer": "Eckels Kladde",
      "category": "Kultur / Musik / Stadtteil",
      "short_description": "Workshop zum Thema wilde Fermente mit praktischen Anleitungen zur Fermentation.",
      "status": "scheduled",
      "source_name": "e.ssenz / Eckels Kladde – alle Kurse und Events",
      "source_url": "https://www.eckels-kladde.de/collections/alle-kurse-und-events-in-munster",
      "source_id": "eckels_kladde_events",
      "confidence": "0,9",
      "last_updated": "2026-06-19T07:47:18.542Z"
    },
    {
      "event_id": "2026-07-05_1530_spiel_zeit_yesterdays_meerwiese_theater",
      "title": "„SPIEL-ZEIT!“ Yesterdays",
      "start_date": "2026-07-05",
      "start_time": "15:30",
      "end_date": "2026-07-05",
      "end_time": null,
      "location_name": "Begegnungszentrum Meerwiese",
      "address": "An der Meerwiese 25, 48157 Münster-Coerde",
      "city": "Münster-Coerde",
      "organizer": "Die Kleine Bürgerbühne",
      "category": "Theater / Kultur / Tanz / Kinderkultur",
      "short_description": "Theaterstück von Reihaneh Youzbashi Dizaji für alle von 8 bis 88 Jahren am 5. Juli 2026 um 15:30 Uhr.",
      "status": "scheduled",
      "source_name": "Meerwiese – Stücke und Termine",
      "source_url": "https://www.stadt-muenster.de/meerwiese/theater/stuecke-und-termine",
      "source_id": "meerwiese_theater",
      "confidence": "0,9",
      "last_updated": "2026-06-19T07:47:18.542Z"
    },
    {
      "event_id": "2026-07-05_1630_konzert_dreier_streicherensembles_meerwiese_begegnungszentrum",
      "title": "Konzert dreier Streicherensembles",
      "start_date": "2026-07-05",
      "start_time": "16:30",
      "end_date": "2026-07-05",
      "end_time": null,
      "location_name": "Begegnungszentrum Meerwiese",
      "address": "An der Meerwiese 25, 48157 Münster-Coerde",
      "city": "Münster-Coerde",
      "organizer": "Westfälische Schule für Musik",
      "category": "Stadtteil / Begegnung / Kultur",
      "short_description": "Die Streichensembles der Westfälischen Schule für Musik präsentieren ein abwechslungsreiches Programm mit einstudierten Stücken. Offen für alle Interessierten.",
      "status": "scheduled",
      "source_name": "Meerwiese – Begegnungszentrum Veranstaltungen",
      "source_url": "https://www.stadt-muenster.de/meerwiese/begegnungszentrum/veranstaltungen",
      "source_id": "meerwiese_begegnungszentrum",
      "confidence": "0,9",
      "last_updated": "2026-06-19T07:47:18.542Z"
    },
    {
      "event_id": "2026-07-06_1430_offener_spieletreff_fur_senior_innen_doppelkopfrunde_alter_werden_in_coerde_awo_coerde_mittendrin",
      "title": "Offener Spieletreff für Senior*innen / Doppelkopfrunde \"Älter werden in Coerde\"",
      "start_date": "2026-07-06",
      "start_time": "14:30",
      "end_date": "2026-07-06",
      "end_time": "17:00",
      "location_name": "AWO Coerde mittendrin",
      "address": "Königsberger Straße 8, 48157 Münster-Coerde",
      "city": "Münster-Coerde",
      "organizer": "AWO Coerde mittendrin",
      "category": "Stadtteil / Begegnung / Beratung",
      "short_description": "Offener Spieletreff für Senior*innen / Doppelkopfrunde \"Älter werden in Coerde\": wöchentliches Angebot jeden Montag im AWO Coerde mittendrin der AWO in Münster-Coerde.",
      "status": "scheduled",
      "source_name": "AWO Coerde mittendrin",
      "source_url": "https://www.awo-msl-re.de/einrichtung/coerde-mittendrin",
      "source_id": "awo_coerde_mittendrin",
      "confidence": "0,9",
      "last_updated": "2026-06-19T07:47:18.542Z"
    },
    {
      "event_id": "2026-07-07_1100_kochprojekt_gemeinsam_am_herd_rezepte_ohne_grenzen_awo_coerde_mittendrin",
      "title": "Kochprojekt „Gemeinsam am Herd – Rezepte ohne Grenzen“",
      "start_date": "2026-07-07",
      "start_time": "11:00",
      "end_date": "2026-07-07",
      "end_time": "14:00",
      "location_name": "AWO Coerde mittendrin",
      "address": "Königsberger Straße 8, 48157 Münster-Coerde",
      "city": "Münster-Coerde",
      "organizer": "AWO Coerde mittendrin",
      "category": "Stadtteil / Begegnung / Beratung",
      "short_description": "Kochprojekt „Gemeinsam am Herd – Rezepte ohne Grenzen“: wöchentliches Angebot jeden Dienstag im AWO Coerde mittendrin der AWO in Münster-Coerde.",
      "status": "scheduled",
      "source_name": "AWO Coerde mittendrin",
      "source_url": "https://www.awo-msl-re.de/einrichtung/coerde-mittendrin",
      "source_id": "awo_coerde_mittendrin",
      "confidence": "0,9",
      "last_updated": "2026-06-19T07:47:18.542Z"
    },
    {
      "event_id": "2026-07-08_0900_migrationsberatung_mbe_in_munster_coerde_drk_munster_migrationsberatung_mbe",
      "title": "Migrationsberatung (MBE) in Münster-Coerde",
      "start_date": "2026-07-08",
      "start_time": "09:00",
      "end_date": "2026-07-08",
      "end_time": "15:00",
      "location_name": "DRK Münster – Migrationsberatung",
      "address": "Hamannplatz 26/28, 48157 Münster-Coerde",
      "city": "Münster-Coerde",
      "organizer": "Deutsches Rotes Kreuz Münster",
      "category": "",
      "short_description": "Wöchentliche Migrationsberatung für erwachsene Neuzugewanderte ab 28 Jahren mit Unterstützung in Integrationsfragen, Behördenangelegenheiten und sozialer Teilhabe, mittwochs von 9 bis 15 Uhr in Coerde.",
      "status": "scheduled",
      "source_name": "DRK Münster – Migrationsberatung (MBE)",
      "source_url": "https://www.drk-muenster.de/angebot/migrationsberatung.html",
      "source_id": "drk_munster_migrationsberatung_mbe",
      "confidence": "0,9",
      "last_updated": "2026-06-19T07:47:18.542Z"
    },
    {
      "event_id": "2026-07-08_1000_fruhstuckstreff_mit_anmeldung_unter_tel_01520_9123615_awo_coerde_mittendrin",
      "title": "Frühstückstreff (mit Anmeldung unter Tel.: 01520 9123615)",
      "start_date": "2026-07-08",
      "start_time": "10:00",
      "end_date": "2026-07-08",
      "end_time": "12:00",
      "location_name": "AWO Coerde mittendrin",
      "address": "Königsberger Straße 8, 48157 Münster-Coerde",
      "city": "Münster-Coerde",
      "organizer": "AWO Coerde mittendrin",
      "category": "Stadtteil / Begegnung / Beratung",
      "short_description": "Frühstückstreff (mit Anmeldung unter Tel.: 01520 9123615): wöchentliches Angebot jeden Mittwoch im AWO Coerde mittendrin der AWO in Münster-Coerde.",
      "status": "scheduled",
      "source_name": "AWO Coerde mittendrin",
      "source_url": "https://www.awo-msl-re.de/einrichtung/coerde-mittendrin",
      "source_id": "awo_coerde_mittendrin",
      "confidence": "0,9",
      "last_updated": "2026-06-19T07:47:18.542Z"
    },
    {
      "event_id": "2026-07-08_1300_wochentliche_offene_beratungszeit_empowerment_rassismuskritik_nachhaltigkeit_koo_iriba_brunnen_termine",
      "title": "Wöchentliche offene Beratungszeit – Empowerment / Rassismuskritik / Nachhaltigkeit & Kooperationen",
      "start_date": "2026-07-08",
      "start_time": "13:00",
      "end_date": "2026-07-08",
      "end_time": "15:00",
      "location_name": "coerde mittendrin",
      "address": "Königsberger Straße 8, 48157 Münster",
      "city": "Münster-Coerde",
      "organizer": "Iriba-Brunnen e.V.",
      "category": "Stadtteil / Begegnung / Engagement",
      "short_description": "Wöchentliche offene Beratungszeit zu Empowerment, Rassismuskritik, Nachhaltigkeit und Kooperationen.",
      "status": "scheduled",
      "source_name": "Iriba-Brunnen – Termine",
      "source_url": "https://www.iriba-brunnen.de/termine/",
      "source_id": "iriba_brunnen_termine",
      "confidence": "0,9",
      "last_updated": "2026-06-19T07:47:18.542Z"
    },
    {
      "event_id": "2026-07-09_1000_demokratissimo_eine_performative_kochshow_meerwiese_theater",
      "title": "Demokratissimo – eine performative Kochshow",
      "start_date": "2026-07-09",
      "start_time": "10:00",
      "end_date": "2026-07-09",
      "end_time": null,
      "location_name": "Begegnungszentrum Meerwiese",
      "address": "An der Meerwiese 25, 48157 Münster-Coerde",
      "city": "Münster-Coerde",
      "organizer": "Fetter Fisch – Performance | Theater aus Münster",
      "category": "Theater / Kultur / Tanz / Kinderkultur",
      "short_description": "Performative Kochshow für alle ab 10 Jahren am 9. Juli 2026 um 10 Uhr, geschlossene Veranstaltung.",
      "status": "scheduled",
      "source_name": "Meerwiese – Stücke und Termine",
      "source_url": "https://www.stadt-muenster.de/meerwiese/theater/stuecke-und-termine",
      "source_id": "meerwiese_theater",
      "confidence": "0,9",
      "last_updated": "2026-06-19T07:47:18.542Z"
    },
    {
      "event_id": "2026-07-09_1100_offene_sprechstunde_coerde_mittendrin_awo_coerde_mittendrin",
      "title": "Offene Sprechstunde „coerde mittendrin“",
      "start_date": "2026-07-09",
      "start_time": "11:00",
      "end_date": "2026-07-09",
      "end_time": "13:00",
      "location_name": "AWO Coerde mittendrin",
      "address": "Königsberger Straße 8, 48157 Münster-Coerde",
      "city": "Münster-Coerde",
      "organizer": "AWO Coerde mittendrin",
      "category": "Stadtteil / Begegnung / Beratung",
      "short_description": "Offene Sprechstunde „coerde mittendrin“: wöchentliches Angebot jeden Donnerstag im AWO Coerde mittendrin der AWO in Münster-Coerde.",
      "status": "scheduled",
      "source_name": "AWO Coerde mittendrin",
      "source_url": "https://www.awo-msl-re.de/einrichtung/coerde-mittendrin",
      "source_id": "awo_coerde_mittendrin",
      "confidence": "0,9",
      "last_updated": "2026-06-19T07:47:18.542Z"
    },
    {
      "event_id": "2026-07-09_1900_zumba_in_coerde_ev_fabi_coerde",
      "title": "Zumba in Coerde",
      "start_date": "2026-07-09",
      "start_time": "19:00",
      "end_date": "2026-07-09",
      "end_time": null,
      "location_name": "Hauptschule Coerde - Musikraum",
      "address": "Münster-Coerde",
      "city": "Münster-Coerde",
      "organizer": "Ev. Familienbildungsstätte Münster",
      "category": "Bildung / Familie / Stadtteil",
      "short_description": "Wöchentlicher Zumba-Kurs in Coerde, beginnend ab dem 16. April 2026, jeweils donnerstags um 19:00 Uhr im Musikraum der Hauptschule Coerde.",
      "status": "scheduled",
      "source_name": "Ev. Familienbildungsstätte Münster – Coerde",
      "source_url": "https://www.ev-fabi-ms.de/programm/fabi-vor-ort/kategorie/Coerde/23",
      "source_id": "ev_fabi_coerde",
      "confidence": "0,9",
      "last_updated": "2026-06-19T07:47:18.542Z"
    },
    {
      "event_id": "2026-07-10_1530_projekt_madchen_starken_awo_coerde_mittendrin",
      "title": "Projekt „Mädchen stärken“",
      "start_date": "2026-07-10",
      "start_time": "15:30",
      "end_date": "2026-07-10",
      "end_time": "17:00",
      "location_name": "AWO Coerde mittendrin",
      "address": "Königsberger Straße 8, 48157 Münster-Coerde",
      "city": "Münster-Coerde",
      "organizer": "AWO Coerde mittendrin",
      "category": "Stadtteil / Begegnung / Beratung",
      "short_description": "Projekt „Mädchen stärken“: wöchentliches Angebot jeden Freitag im AWO Coerde mittendrin der AWO in Münster-Coerde.",
      "status": "scheduled",
      "source_name": "AWO Coerde mittendrin",
      "source_url": "https://www.awo-msl-re.de/einrichtung/coerde-mittendrin",
      "source_id": "awo_coerde_mittendrin",
      "confidence": "0,9",
      "last_updated": "2026-06-19T07:47:18.542Z"
    },
    {
      "event_id": "2026-07-11_1400_coerdinale_das_kulturfest_im_stadtteil_kulturinitiative_coerde",
      "title": "Coerdinale – Das Kulturfest im Stadtteil",
      "start_date": "2026-07-11",
      "start_time": "14:00",
      "end_date": "2026-07-11",
      "end_time": "22:00",
      "location_name": "Begegnungszentrum Meerwiese",
      "address": "An der Meerwiese 25, 48157, Münster",
      "city": "Münster-Coerde",
      "organizer": "Kulturinitiative Coerde e. V.",
      "category": "Kultur / Stadtteil / Ehrenamt",
      "short_description": "| Coerdinale – Das Kulturfest im Stadtteil kostenfrei Kulturinitiative Coerde e. V. Veranstalter-Website anzeigen u tu - oe de Zum Kalender hinzufügen Google Kalender iCalendar Outlook 365 Outlook Live",
      "status": "scheduled",
      "source_name": "Kulturinitiative Coerde",
      "source_url": "https://kulturinitiative-coerde.de/",
      "source_id": "kulturinitiative_coerde",
      "confidence": "0,9",
      "last_updated": "2026-06-19T07:47:18.542Z"
    },
    {
      "event_id": "2026-07-11_1500_nachhilfeangebot_awo_coerde_mittendrin",
      "title": "Nachhilfeangebot",
      "start_date": "2026-07-11",
      "start_time": "15:00",
      "end_date": "2026-07-11",
      "end_time": "17:00",
      "location_name": "AWO Coerde mittendrin",
      "address": "Königsberger Straße 8, 48157 Münster-Coerde",
      "city": "Münster-Coerde",
      "organizer": "AWO Coerde mittendrin",
      "category": "Stadtteil / Begegnung / Beratung",
      "short_description": "Nachhilfeangebot: wöchentliches Angebot jeden Samstag im AWO Coerde mittendrin der AWO in Münster-Coerde.",
      "status": "scheduled",
      "source_name": "AWO Coerde mittendrin",
      "source_url": "https://www.awo-msl-re.de/einrichtung/coerde-mittendrin",
      "source_id": "awo_coerde_mittendrin",
      "confidence": "0,9",
      "last_updated": "2026-06-19T07:47:18.542Z"
    },
    {
      "event_id": "2026-07-12_1530_spiel_zeit_was_fur_ein_theater_meerwiese_theater",
      "title": "„SPIEL-ZEIT!“ Was für ein Theater?",
      "start_date": "2026-07-12",
      "start_time": "15:30",
      "end_date": "2026-07-12",
      "end_time": null,
      "location_name": "Begegnungszentrum Meerwiese",
      "address": "An der Meerwiese 25, 48157 Münster-Coerde",
      "city": "Münster-Coerde",
      "organizer": "Meerwiesel Theaterkinderclub",
      "category": "Theater / Kultur / Tanz / Kinderkultur",
      "short_description": "Eigenproduktion des Theaterkinderclub Meerwiesel für alle ab 8 Jahren am 12. Juli 2026 um 15:30 Uhr.",
      "status": "scheduled",
      "source_name": "Meerwiese – Stücke und Termine",
      "source_url": "https://www.stadt-muenster.de/meerwiese/theater/stuecke-und-termine",
      "source_id": "meerwiese_theater",
      "confidence": "0,9",
      "last_updated": "2026-06-19T07:47:18.542Z"
    },
    {
      "event_id": "2026-07-13_1430_offener_spieletreff_fur_senior_innen_doppelkopfrunde_alter_werden_in_coerde_awo_coerde_mittendrin",
      "title": "Offener Spieletreff für Senior*innen / Doppelkopfrunde \"Älter werden in Coerde\"",
      "start_date": "2026-07-13",
      "start_time": "14:30",
      "end_date": "2026-07-13",
      "end_time": "17:00",
      "location_name": "AWO Coerde mittendrin",
      "address": "Königsberger Straße 8, 48157 Münster-Coerde",
      "city": "Münster-Coerde",
      "organizer": "AWO Coerde mittendrin",
      "category": "Stadtteil / Begegnung / Beratung",
      "short_description": "Offener Spieletreff für Senior*innen / Doppelkopfrunde \"Älter werden in Coerde\": wöchentliches Angebot jeden Montag im AWO Coerde mittendrin der AWO in Münster-Coerde.",
      "status": "scheduled",
      "source_name": "AWO Coerde mittendrin",
      "source_url": "https://www.awo-msl-re.de/einrichtung/coerde-mittendrin",
      "source_id": "awo_coerde_mittendrin",
      "confidence": "0,9",
      "last_updated": "2026-06-19T07:47:18.542Z"
    },
    {
      "event_id": "2026-07-14_1100_kochprojekt_gemeinsam_am_herd_rezepte_ohne_grenzen_awo_coerde_mittendrin",
      "title": "Kochprojekt „Gemeinsam am Herd – Rezepte ohne Grenzen“",
      "start_date": "2026-07-14",
      "start_time": "11:00",
      "end_date": "2026-07-14",
      "end_time": "14:00",
      "location_name": "AWO Coerde mittendrin",
      "address": "Königsberger Straße 8, 48157 Münster-Coerde",
      "city": "Münster-Coerde",
      "organizer": "AWO Coerde mittendrin",
      "category": "Stadtteil / Begegnung / Beratung",
      "short_description": "Kochprojekt „Gemeinsam am Herd – Rezepte ohne Grenzen“: wöchentliches Angebot jeden Dienstag im AWO Coerde mittendrin der AWO in Münster-Coerde.",
      "status": "scheduled",
      "source_name": "AWO Coerde mittendrin",
      "source_url": "https://www.awo-msl-re.de/einrichtung/coerde-mittendrin",
      "source_id": "awo_coerde_mittendrin",
      "confidence": "0,9",
      "last_updated": "2026-06-19T07:47:18.542Z"
    },
    {
      "event_id": "2026-07-15_0900_migrationsberatung_mbe_in_munster_coerde_drk_munster_migrationsberatung_mbe",
      "title": "Migrationsberatung (MBE) in Münster-Coerde",
      "start_date": "2026-07-15",
      "start_time": "09:00",
      "end_date": "2026-07-15",
      "end_time": "15:00",
      "location_name": "DRK Münster – Migrationsberatung",
      "address": "Hamannplatz 26/28, 48157 Münster-Coerde",
      "city": "Münster-Coerde",
      "organizer": "Deutsches Rotes Kreuz Münster",
      "category": "",
      "short_description": "Wöchentliche Migrationsberatung für erwachsene Neuzugewanderte ab 28 Jahren mit Unterstützung in Integrationsfragen, Behördenangelegenheiten und sozialer Teilhabe, mittwochs von 9 bis 15 Uhr in Coerde.",
      "status": "scheduled",
      "source_name": "DRK Münster – Migrationsberatung (MBE)",
      "source_url": "https://www.drk-muenster.de/angebot/migrationsberatung.html",
      "source_id": "drk_munster_migrationsberatung_mbe",
      "confidence": "0,9",
      "last_updated": "2026-06-19T07:47:18.542Z"
    },
    {
      "event_id": "2026-07-15_1000_fruhstuckstreff_mit_anmeldung_unter_tel_01520_9123615_awo_coerde_mittendrin",
      "title": "Frühstückstreff (mit Anmeldung unter Tel.: 01520 9123615)",
      "start_date": "2026-07-15",
      "start_time": "10:00",
      "end_date": "2026-07-15",
      "end_time": "12:00",
      "location_name": "AWO Coerde mittendrin",
      "address": "Königsberger Straße 8, 48157 Münster-Coerde",
      "city": "Münster-Coerde",
      "organizer": "AWO Coerde mittendrin",
      "category": "Stadtteil / Begegnung / Beratung",
      "short_description": "Frühstückstreff (mit Anmeldung unter Tel.: 01520 9123615): wöchentliches Angebot jeden Mittwoch im AWO Coerde mittendrin der AWO in Münster-Coerde.",
      "status": "scheduled",
      "source_name": "AWO Coerde mittendrin",
      "source_url": "https://www.awo-msl-re.de/einrichtung/coerde-mittendrin",
      "source_id": "awo_coerde_mittendrin",
      "confidence": "0,9",
      "last_updated": "2026-06-19T07:47:18.542Z"
    },
    {
      "event_id": "2026-07-15_1300_wochentliche_offene_beratungszeit_empowerment_rassismuskritik_nachhaltigkeit_koo_iriba_brunnen_termine",
      "title": "Wöchentliche offene Beratungszeit – Empowerment / Rassismuskritik / Nachhaltigkeit & Kooperationen",
      "start_date": "2026-07-15",
      "start_time": "13:00",
      "end_date": "2026-07-15",
      "end_time": "15:00",
      "location_name": "coerde mittendrin",
      "address": "Königsberger Straße 8, 48157 Münster",
      "city": "Münster-Coerde",
      "organizer": "Iriba-Brunnen e.V.",
      "category": "Stadtteil / Begegnung / Engagement",
      "short_description": "Wöchentliche offene Beratungszeit zu Empowerment, Rassismuskritik, Nachhaltigkeit und Kooperationen.",
      "status": "scheduled",
      "source_name": "Iriba-Brunnen – Termine",
      "source_url": "https://www.iriba-brunnen.de/termine/",
      "source_id": "iriba_brunnen_termine",
      "confidence": "0,9",
      "last_updated": "2026-06-19T07:47:18.542Z"
    },
    {
      "event_id": "2026-07-16_1100_offene_sprechstunde_coerde_mittendrin_awo_coerde_mittendrin",
      "title": "Offene Sprechstunde „coerde mittendrin“",
      "start_date": "2026-07-16",
      "start_time": "11:00",
      "end_date": "2026-07-16",
      "end_time": "13:00",
      "location_name": "AWO Coerde mittendrin",
      "address": "Königsberger Straße 8, 48157 Münster-Coerde",
      "city": "Münster-Coerde",
      "organizer": "AWO Coerde mittendrin",
      "category": "Stadtteil / Begegnung / Beratung",
      "short_description": "Offene Sprechstunde „coerde mittendrin“: wöchentliches Angebot jeden Donnerstag im AWO Coerde mittendrin der AWO in Münster-Coerde.",
      "status": "scheduled",
      "source_name": "AWO Coerde mittendrin",
      "source_url": "https://www.awo-msl-re.de/einrichtung/coerde-mittendrin",
      "source_id": "awo_coerde_mittendrin",
      "confidence": "0,9",
      "last_updated": "2026-06-19T07:47:18.542Z"
    },
    {
      "event_id": "2026-07-16_1900_zumba_in_coerde_ev_fabi_coerde",
      "title": "Zumba in Coerde",
      "start_date": "2026-07-16",
      "start_time": "19:00",
      "end_date": "2026-07-16",
      "end_time": null,
      "location_name": "Hauptschule Coerde - Musikraum",
      "address": "Münster-Coerde",
      "city": "Münster-Coerde",
      "organizer": "Ev. Familienbildungsstätte Münster",
      "category": "Bildung / Familie / Stadtteil",
      "short_description": "Wöchentlicher Zumba-Kurs in Coerde, beginnend ab dem 16. April 2026, jeweils donnerstags um 19:00 Uhr im Musikraum der Hauptschule Coerde.",
      "status": "scheduled",
      "source_name": "Ev. Familienbildungsstätte Münster – Coerde",
      "source_url": "https://www.ev-fabi-ms.de/programm/fabi-vor-ort/kategorie/Coerde/23",
      "source_id": "ev_fabi_coerde",
      "confidence": "0,9",
      "last_updated": "2026-06-19T07:47:18.542Z"
    },
    {
      "event_id": "2026-07-17_0415_lesen_mit_kleinen_wesen_stadtbuecherei_coerde",
      "title": "Lesen mit kleinen Wesen",
      "start_date": "2026-07-17",
      "start_time": "04:15",
      "end_date": "2026-07-17",
      "end_time": null,
      "location_name": "Stadtbücherei Coerde",
      "address": "Hamannplatz, 48157 Münster",
      "city": "Münster-Coerde",
      "organizer": "Stadtbücherei Münster",
      "category": "Lesung / Bildung / Stadtteil",
      "short_description": "Vorlesestunde für Kleinkinder mit Eltern oder Tageseltern, altersgerechte Geschichten gemütlich vorgelesen.",
      "status": "scheduled",
      "source_name": "Stadtbücherei Coerde – Veranstaltungen",
      "source_url": "https://www.stadt-muenster.de/buecherei/orte-und-oeffnungszeiten/coerde/veranstaltungen",
      "source_id": "stadtbuecherei_coerde",
      "confidence": "0,9",
      "last_updated": "2026-06-19T07:47:18.542Z"
    },
    {
      "event_id": "2026-07-17_1530_projekt_madchen_starken_awo_coerde_mittendrin",
      "title": "Projekt „Mädchen stärken“",
      "start_date": "2026-07-17",
      "start_time": "15:30",
      "end_date": "2026-07-17",
      "end_time": "17:00",
      "location_name": "AWO Coerde mittendrin",
      "address": "Königsberger Straße 8, 48157 Münster-Coerde",
      "city": "Münster-Coerde",
      "organizer": "AWO Coerde mittendrin",
      "category": "Stadtteil / Begegnung / Beratung",
      "short_description": "Projekt „Mädchen stärken“: wöchentliches Angebot jeden Freitag im AWO Coerde mittendrin der AWO in Münster-Coerde.",
      "status": "scheduled",
      "source_name": "AWO Coerde mittendrin",
      "source_url": "https://www.awo-msl-re.de/einrichtung/coerde-mittendrin",
      "source_id": "awo_coerde_mittendrin",
      "confidence": "0,9",
      "last_updated": "2026-06-19T07:47:18.542Z"
    },
    {
      "event_id": "2026-07-29_1700_burgerkurs_vom_patty_bis_zur_sauce_selbstgemacht_eckels_kladde_events",
      "title": "Burgerkurs - Vom Patty bis zur Sauce selbstgemacht",
      "start_date": "2026-07-29",
      "start_time": "17:00",
      "end_date": "2026-07-29",
      "end_time": "22:00",
      "location_name": "Eckels Kladde",
      "address": "Coermühle 50f",
      "city": "Münster-Coerde",
      "organizer": "Eckels Kladde",
      "category": "Kultur / Musik / Stadtteil",
      "short_description": "Kurs zur Herstellung von Burgern inklusive Pattys und Saucen.",
      "status": "scheduled",
      "source_name": "e.ssenz / Eckels Kladde – alle Kurse und Events",
      "source_url": "https://www.eckels-kladde.de/collections/alle-kurse-und-events-in-munster",
      "source_id": "eckels_kladde_events",
      "confidence": "0,9",
      "last_updated": "2026-06-19T07:47:18.542Z"
    },
    {
      "event_id": "2026-08-26_1700_burgerkurs_vom_patty_bis_zur_sauce_selbstgemacht_eckels_kladde_events",
      "title": "Burgerkurs - Vom Patty bis zur Sauce selbstgemacht",
      "start_date": "2026-08-26",
      "start_time": "17:00",
      "end_date": "2026-08-26",
      "end_time": "22:00",
      "location_name": "Eckels Kladde",
      "address": "Coermühle 50f",
      "city": "Münster-Coerde",
      "organizer": "Eckels Kladde",
      "category": "Kultur / Musik / Stadtteil",
      "short_description": "Kurs zur Herstellung von Burgern inklusive Pattys und Saucen.",
      "status": "scheduled",
      "source_name": "e.ssenz / Eckels Kladde – alle Kurse und Events",
      "source_url": "https://www.eckels-kladde.de/collections/alle-kurse-und-events-in-munster",
      "source_id": "eckels_kladde_events",
      "confidence": "0,9",
      "last_updated": "2026-06-19T07:47:18.542Z"
    },
    {
      "event_id": "2026-08-29_1500_abschlussfest_des_coerder_kinder_kultur_sommers_2026_initiative_chack_projekte",
      "title": "Abschlussfest des Coerder-Kinder-Kultur-Sommers 2026",
      "start_date": "2026-08-29",
      "start_time": "15:00",
      "end_date": "2026-08-29",
      "end_time": null,
      "location_name": "Hamannplatz",
      "address": "Münster-Coerde",
      "city": "Münster-Coerde",
      "organizer": "Initiative ChaCK e.V.",
      "category": "",
      "short_description": "Abschlussfest des Coerder-Kinder-Kultur-Sommers 2026 mit Präsentationen der Kinder aus den Sommerkursen auf dem Hamannplatz in Münster-Coerde.",
      "status": "scheduled",
      "source_name": "Initiative ChaCK – Projekte",
      "source_url": "",
      "source_id": "initiative_chack_projekte",
      "confidence": "0,9",
      "last_updated": "2026-06-19T07:47:18.542Z"
    },
    {
      "event_id": "2026-09-04_1000_tanzxchange_freie_tanzszene_munster_open_class_meerwiese_begegnungszentrum",
      "title": "TanzXchange – Freie Tanzszene Münster: OPEN CLASS",
      "start_date": "2026-09-04",
      "start_time": "10:00",
      "end_date": "2026-09-04",
      "end_time": "12:00",
      "location_name": "Begegnungszentrum Meerwiese",
      "address": "An der Meerwiese 25, 48157 Münster-Coerde",
      "city": "Münster-Coerde",
      "organizer": "Melanie López López, Tänzerin und Mitbegründerin des Kollektivergissmeinnicht",
      "category": "Stadtteil / Begegnung / Kultur",
      "short_description": "Offene Tanzklasse als Teil der TanzXchange-Initiative zur Förderung der Tanzszene in Münster.",
      "status": "scheduled",
      "source_name": "Meerwiese – Begegnungszentrum Veranstaltungen",
      "source_url": "https://www.stadt-muenster.de/meerwiese/begegnungszentrum/veranstaltungen",
      "source_id": "meerwiese_begegnungszentrum",
      "confidence": "0,9",
      "last_updated": "2026-06-19T07:47:18.542Z"
    },
    {
      "event_id": "2026-09-04_1900_die_lofoten_eckels_kladde_events",
      "title": "Die Lofoten",
      "start_date": "2026-09-04",
      "start_time": "19:00",
      "end_date": "2026-09-04",
      "end_time": null,
      "location_name": "Eckels Kladde",
      "address": "Coermühle 50f",
      "city": "Münster-Coerde",
      "organizer": "Eckels Kladde",
      "category": "Kultur / Musik / Stadtteil",
      "short_description": "Multimediale Präsentation mit einem einzigartigen 3-Gang-Menü.",
      "status": "scheduled",
      "source_name": "e.ssenz / Eckels Kladde – alle Kurse und Events",
      "source_url": "https://www.eckels-kladde.de/collections/alle-kurse-und-events-in-munster",
      "source_id": "eckels_kladde_events",
      "confidence": "0,9",
      "last_updated": "2026-06-19T07:47:18.542Z"
    },
    {
      "event_id": "2026-09-05_1500_fest_der_vielfalt_iriba_brunnen_termine",
      "title": "Fest der Vielfalt",
      "start_date": "2026-09-05",
      "start_time": "15:00",
      "end_date": "2026-09-05",
      "end_time": "21:00",
      "location_name": "Franziskushaus in Coerde",
      "address": "Schneidemühlerstr. 23, 48157 Münster",
      "city": "Münster-Coerde",
      "organizer": "Iriba-Brunnen e.V.",
      "category": "Stadtteil / Begegnung / Engagement",
      "short_description": "Vielfältiges Fest mit kulturellen Angeboten und Begegnungen im Franziskushaus Coerde.",
      "status": "scheduled",
      "source_name": "Iriba-Brunnen – Termine",
      "source_url": "https://www.iriba-brunnen.de/termine/",
      "source_id": "iriba_brunnen_termine",
      "confidence": "0,9",
      "last_updated": "2026-06-19T07:47:18.542Z"
    },
    {
      "event_id": "2026-09-06_1200_qi_gong_seminar_die_wandlungsphase_metall_meerwiese_begegnungszentrum",
      "title": "Qi Gong – Seminar Die Wandlungsphase Metall",
      "start_date": "2026-09-06",
      "start_time": "12:00",
      "end_date": "2026-09-06",
      "end_time": "19:00",
      "location_name": "Begegnungszentrum Meerwiese",
      "address": "An der Meerwiese 25, 48157 Münster-Coerde",
      "city": "Münster-Coerde",
      "organizer": "Volker Nowak-von der Way, Qi Gong – Lehrer",
      "category": "Stadtteil / Begegnung / Kultur",
      "short_description": "Seminar mit Atemübungen und Selbstmassagetechniken zur Stärkung der Lunge und des Immunsystems. Vorkenntnisse nicht erforderlich.",
      "status": "scheduled",
      "source_name": "Meerwiese – Begegnungszentrum Veranstaltungen",
      "source_url": "https://www.stadt-muenster.de/meerwiese/begegnungszentrum/veranstaltungen",
      "source_id": "meerwiese_begegnungszentrum",
      "confidence": "0,9",
      "last_updated": "2026-06-19T07:47:18.542Z"
    },
    {
      "event_id": "2026-09-18_1930_vorlese_cafe_im_september_auf_turkisch_deutsch_mit_musik_kulturinitiative_coerde",
      "title": "Vorlese-Café im September auf Türkisch & Deutsch mit Musik",
      "start_date": "2026-09-18",
      "start_time": "19:30",
      "end_date": "2026-09-18",
      "end_time": "21:00",
      "location_name": "Begegnungszentrum Meerwiese",
      "address": "An der Meerwiese 25, 48157, Münster",
      "city": "Münster-Coerde",
      "organizer": "Kulturinitiative Coerde e. V.",
      "category": "Kultur / Stadtteil / Ehrenamt",
      "short_description": "| Muttersprachler*innen nehmen ihr Publikum mit auf eine Entdeckungsreise in andere Kulturen und literarische Welten. Die Zuhörer*nnen sind eingeladen, dem Klang der fremden Wörter, Texte oder Musik zu lauschen und sich von unbekannten Sprachmelodien verführen zu lassen. Anschließend erfolgt die Übe",
      "status": "scheduled",
      "source_name": "Kulturinitiative Coerde",
      "source_url": "https://kulturinitiative-coerde.de/",
      "source_id": "kulturinitiative_coerde",
      "confidence": "0,9",
      "last_updated": "2026-06-19T07:47:18.542Z"
    },
    {
      "event_id": "2026-09-19_ganztag_6_rock_am_berg_jubilaum_rock_am_berg",
      "title": "6. Rock am Berg Jubiläum",
      "start_date": "2026-09-19",
      "start_time": null,
      "end_date": "2026-09-19",
      "end_time": null,
      "location_name": "Rieselfelder Münster",
      "address": "Münster-Coerde",
      "city": "Münster-Coerde",
      "organizer": "Rock am Berg Münster",
      "category": "Musik / Konzert / Stadtteil",
      "short_description": "Benefizkonzert mit mehreren Bands ohne Gage zur Unterstützung von Menschen in Not in Münster und dem Münsterland. Getränke und Speisen werden vor Ort angeboten.",
      "status": "scheduled",
      "source_name": "Rock am Berg",
      "source_url": "https://www.rockamberg-ms.de/",
      "source_id": "rock_am_berg",
      "confidence": "0,9",
      "last_updated": "2026-06-19T07:47:18.542Z"
    },
    {
      "event_id": "2026-09-19_1400_osteuropa_seminar_nie_wieder_allein_meerwiese_begegnungszentrum",
      "title": "Osteuropa – Seminar: Nie wieder allein",
      "start_date": "2026-09-19",
      "start_time": "14:00",
      "end_date": "2026-09-20",
      "end_time": "14:00",
      "location_name": "Begegnungszentrum Meerwiese",
      "address": "An der Meerwiese 25, 48157 Münster-Coerde",
      "city": "Münster-Coerde",
      "organizer": "Joachim Wieder, Experte Osteuropäische Geschichte und internationale Politik",
      "category": "Stadtteil / Begegnung / Kultur",
      "short_description": "Seminar zur Entwicklung eines neuartigen Patriotismus in Osteuropa, insbesondere im Baltikum, der Ukraine und Polen. Diskussion über friedliche Überwindung historischer Konflikte.",
      "status": "scheduled",
      "source_name": "Meerwiese – Begegnungszentrum Veranstaltungen",
      "source_url": "https://www.stadt-muenster.de/meerwiese/begegnungszentrum/veranstaltungen",
      "source_id": "meerwiese_begegnungszentrum",
      "confidence": "0,9",
      "last_updated": "2026-06-19T07:47:18.542Z"
    },
    {
      "event_id": "2026-10-09_1130_ich_bin_mehr_als_mein_feed_workshop_fur_madchen_zu_social_media_essen_korpergefu_iriba_brunnen_termine",
      "title": "„Ich bin mehr als mein Feed“ – Workshop für Mädchen zu Social Media, Essen & Körpergefühl",
      "start_date": "2026-10-09",
      "start_time": "11:30",
      "end_date": "2026-10-09",
      "end_time": "17:30",
      "location_name": "coerde mittendrin",
      "address": "",
      "city": "Münster-Coerde",
      "organizer": "Iriba-Brunnen e.V.",
      "category": "Stadtteil / Begegnung / Engagement",
      "short_description": "Workshop für Mädchen zu den Themen Social Media, Ernährung und Körperbewusstsein.",
      "status": "scheduled",
      "source_name": "Iriba-Brunnen – Termine",
      "source_url": "https://www.iriba-brunnen.de/termine/",
      "source_id": "iriba_brunnen_termine",
      "confidence": "0,9",
      "last_updated": "2026-06-19T07:47:18.542Z"
    },
    {
      "event_id": "2026-10-10_1000_tagung_fruhkindliche_bildung_und_chancengleichheit_initiative_chack_fachtagung",
      "title": "Tagung: Frühkindliche Bildung und Chancengleichheit",
      "start_date": "2026-10-10",
      "start_time": "10:00",
      "end_date": "2026-10-10",
      "end_time": "15:30",
      "location_name": "Hörsaal F1, Fürstenberghaus",
      "address": "Domplatz 20-22, Münster-Coerde",
      "city": "Münster-Coerde",
      "organizer": "Initiative ChaCK e.V.",
      "category": "",
      "short_description": "Fachtagung mit internationalen Wissenschaftlern und Experten zu frühkindlicher Bildung und Chancengleichheit. Inklusive Vorträgen und Podiumsdiskussion zum Thema Kinderarmut. Teilnahme kostenlos und offen für alle Interessierten.",
      "status": "scheduled",
      "source_name": "Initiative ChaCK – Fachtagung",
      "source_url": "",
      "source_id": "initiative_chack_fachtagung",
      "confidence": "0,9",
      "last_updated": "2026-06-19T07:47:18.542Z"
    },
    {
      "event_id": "2026-11-06_1900_die_lofoten_eckels_kladde_events",
      "title": "Die Lofoten",
      "start_date": "2026-11-06",
      "start_time": "19:00",
      "end_date": "2026-11-06",
      "end_time": null,
      "location_name": "Eckels Kladde",
      "address": "Coermühle 50f",
      "city": "Münster-Coerde",
      "organizer": "Eckels Kladde",
      "category": "Kultur / Musik / Stadtteil",
      "short_description": "Multimediale Präsentation mit einem einzigartigen 3-Gang-Menü.",
      "status": "scheduled",
      "source_name": "e.ssenz / Eckels Kladde – alle Kurse und Events",
      "source_url": "https://www.eckels-kladde.de/collections/alle-kurse-und-events-in-munster",
      "source_id": "eckels_kladde_events",
      "confidence": "0,9",
      "last_updated": "2026-06-19T07:47:18.542Z"
    },
    {
      "event_id": "2026-11-06_1930_vorlese_cafe_im_november_auf_russisch_deutsch_mit_musik_kulturinitiative_coerde",
      "title": "Vorlese-Café im November auf Russisch & Deutsch mit Musik",
      "start_date": "2026-11-06",
      "start_time": "19:30",
      "end_date": "2026-11-06",
      "end_time": "21:00",
      "location_name": "Begegnungszentrum Meerwiese",
      "address": "An der Meerwiese 25, 48157, Münster",
      "city": "Münster-Coerde",
      "organizer": "Kulturinitiative Coerde e. V.",
      "category": "Kultur / Stadtteil / Ehrenamt",
      "short_description": "| Muttersprachler*innen nehmen ihr Publikum mit auf eine Entdeckungsreise in andere Kulturen und literarische Welten. Die Zuhörer*nnen sind eingeladen, dem Klang der fremden Wörter, Texte oder Musik zu lauschen und sich von unbekannten Sprachmelodien verführen zu lassen. Anschließend erfolgt die Übe",
      "status": "scheduled",
      "source_name": "Kulturinitiative Coerde",
      "source_url": "https://kulturinitiative-coerde.de/",
      "source_id": "kulturinitiative_coerde",
      "confidence": "0,9",
      "last_updated": "2026-06-19T07:47:18.542Z"
    },
    {
      "event_id": "2026-11-20_0415_lesen_mit_kleinen_wesen_stadtbuecherei_coerde",
      "title": "Lesen mit kleinen Wesen",
      "start_date": "2026-11-20",
      "start_time": "04:15",
      "end_date": "2026-11-20",
      "end_time": null,
      "location_name": "Stadtbücherei Coerde",
      "address": "Hamannplatz, 48157 Münster",
      "city": "Münster-Coerde",
      "organizer": "Stadtbücherei Münster",
      "category": "Lesung / Bildung / Stadtteil",
      "short_description": "Vorlesestunde für Kleinkinder mit Eltern oder Tageseltern, altersgerechte Geschichten gemütlich vorgelesen.",
      "status": "scheduled",
      "source_name": "Stadtbücherei Coerde – Veranstaltungen",
      "source_url": "https://www.stadt-muenster.de/buecherei/orte-und-oeffnungszeiten/coerde/veranstaltungen",
      "source_id": "stadtbuecherei_coerde",
      "confidence": "0,9",
      "last_updated": "2026-06-19T07:47:18.542Z"
    },
    {
      "event_id": "2026-12-18_0415_lesen_mit_kleinen_wesen_stadtbuecherei_coerde",
      "title": "Lesen mit kleinen Wesen",
      "start_date": "2026-12-18",
      "start_time": "04:15",
      "end_date": "2026-12-18",
      "end_time": null,
      "location_name": "Stadtbücherei Coerde",
      "address": "Hamannplatz, 48157 Münster",
      "city": "Münster-Coerde",
      "organizer": "Stadtbücherei Münster",
      "category": "Lesung / Bildung / Stadtteil",
      "short_description": "Vorlesestunde für Kleinkinder mit Eltern oder Tageseltern, altersgerechte Geschichten gemütlich vorgelesen.",
      "status": "scheduled",
      "source_name": "Stadtbücherei Coerde – Veranstaltungen",
      "source_url": "https://www.stadt-muenster.de/buecherei/orte-und-oeffnungszeiten/coerde/veranstaltungen",
      "source_id": "stadtbuecherei_coerde",
      "confidence": "0,9",
      "last_updated": "2026-06-19T07:47:18.542Z"
    }
  ]
}
